sorarepy/__init__.py
sorarepy/_nbdev.py
sorarepy/login.py
sorarepy-0.0.1.dist-info/LICENSE
sorarepy-0.0.1.dist-info/METADATA
sorarepy-0.0.1.dist-info/WHEEL
sorarepy-0.0.1.dist-info/top_level.txt
sorarepy-0.0.1.dist-info/RECORD
