Metadata-Version: 2.1
Name: sorarepy
Version: 0.0.1
Summary: A python wrapper for the Sorare API.
Home-page: https://github.com/seanyboi/sorarepy/tree/master/
Author: Sean O'Connor
Author-email: oconnorjamessean@gmail.com
License: Apache Software License 2.0
Keywords: sorare python api graphql football baseball
Classifier: Development Status :: 3 - Alpha
Classifier: Intended Audience :: Developers
Classifier: Natural Language :: English
Classifier: Programming Language :: Python :: 3.7
Classifier: Programming Language :: Python :: 3.8
Classifier: Programming Language :: Python :: 3.9
Classifier: Programming Language :: Python :: 3.10
Classifier: License :: OSI Approved :: Apache Software License
Requires-Python: >=3.7
License-File: LICENSE
Requires-Dist: pip
Requires-Dist: packaging
Requires-Dist: requests
Requires-Dist: bcrypt
Provides-Extra: dev
